video_to_text_VTT/__init__.py
video_to_text_VTT/__main__.py
video_to_text_vtt-0.1.0.dist-info/entry_points.txt
video_to_text_vtt-0.1.0.dist-info/LICENSE
video_to_text_vtt-0.1.0.dist-info/WHEEL
video_to_text_vtt-0.1.0.dist-info/METADATA
video_to_text_vtt-0.1.0.dist-info/RECORD
